{
  "sections": {
    "16578343597132b44e": {
      "type": "mobile-extra-nav",
      "settings": {
        "extra_nav_menu": "extra-mobile-nav-menu"
      }
    },
    "main": {
      "type": "main-product",
      "blocks": {
        "product_meta": {
          "type": "product_meta",
          "settings": {
            "show_vendor": false,
            "show_sku": false,
            "show_product_rating": true,
            "show_taxes_included": false
          }
        },
        "variant_selector": {
          "type": "variant_selector",
          "settings": {
            "selector_mode": "block",
            "show_color_swatch": true,
            "show_color_carousel": false,
            "size_chart": ""
          }
        },
        "dadadb73-3c29-44d1-92cb-5186449a041e": {
          "type": "key_details",
          "settings": {
          }
        },
        "buy_buttons": {
          "type": "buy_buttons",
          "settings": {
            "show_price_in_button": false,
            "show_payment_button": false
          }
        },
        "description": {
          "type": "description",
          "settings": {
          }
        },
        "share_buttons": {
          "type": "share_buttons",
          "disabled": true,
          "settings": {
          }
        },
        "487620e0-d458-48a1-8c1f-43587657e53d": {
          "type": "buy_it_with",
          "settings": {
            "product": "{{ product.metafields.custom.cross_promoted_product.value }}",
            "title": "Pair it with"
          }
        }
      },
      "block_order": [
        "product_meta",
        "variant_selector",
        "dadadb73-3c29-44d1-92cb-5186449a041e",
        "buy_buttons",
        "description",
        "share_buttons",
        "487620e0-d458-48a1-8c1f-43587657e53d"
      ],
      "settings": {
        "image_size": "small",
        "pillarbox_enabled": true,
        "stack_images": false,
        "show_thumbnails": true,
        "enable_image_zoom": true,
        "enable_video_looping": false
      }
    },
    "1657649384c14394b7": {
      "type": "apps",
      "blocks": {
        "b2cdce1d-0de1-420d-b140-2f3557e58dfc": {
          "type": "shopify:\/\/apps\/stamped-product-reviews-ugc\/blocks\/main-widget\/a103faaf-2125-4b0e-89fa-de5149736723",
          "settings": {
            "animation": true,
            "tags_exclude": "",
            "tags_include": "",
            "search": "",
            "linkify": true,
            "use_metafields": true,
            "sku_tagtype": "sku"
          }
        }
      },
      "block_order": [
        "b2cdce1d-0de1-420d-b140-2f3557e58dfc"
      ],
      "settings": {
        "include_margins": true
      }
    },
    "product-recommendations": {
      "type": "product-recommendations",
      "settings": {
        "heading": "You may also like",
        "show_product_info": true,
        "show_vendor": false,
        "show_color_swatch": false
      }
    },
    "recently-viewed-products": {
      "type": "recently-viewed-products",
      "settings": {
        "title": "Recently viewed",
        "show_product_info": true,
        "show_vendor": false,
        "show_color_swatch": false
      }
    }
  },
  "order": [
    "16578343597132b44e",
    "main",
    "1657649384c14394b7",
    "product-recommendations",
    "recently-viewed-products"
  ]
}
